zeeker/__init__.py
zeeker/cli.py
zeeker/commands/__init__.py
zeeker/commands/assets.py
zeeker/commands/backup.py
zeeker/commands/helpers.py
zeeker/commands/metadata.py
zeeker/core/__init__.py
zeeker/core/deployer.py
zeeker/core/generator.py
zeeker/core/metadata.py
zeeker/core/project.py
zeeker/core/resources.py
zeeker/core/scaffolding.py
zeeker/core/schema.py
zeeker/core/templates.py
zeeker/core/types.py
zeeker/core/validator.py
zeeker/core/database/__init__.py
zeeker/core/database/async_executor.py
zeeker/core/database/builder.py
zeeker/core/database/fts_processor.py
zeeker/core/database/processor.py
zeeker/core/database/s3_sync.py
zeeker/templates/fragments.py.j2
zeeker/templates/fragments_async.py.j2
zeeker/templates/resource.py.j2
zeeker/templates/resource_async.py.j2
zeeker-0.5.1.dist-info/METADATA
zeeker-0.5.1.dist-info/WHEEL
zeeker-0.5.1.dist-info/entry_points.txt
zeeker-0.5.1.dist-info/RECORD
