Metadata-Version: 2.4
Name: zeeker
Version: 0.5.1
Summary: Add your description here
License-Expression: MIT
Requires-Python: >=3.12
Requires-Dist: boto3>=1.38.32
Requires-Dist: click>=8.2.1
Requires-Dist: jinja2>=3.1.6
Requires-Dist: python-dotenv>=1.0.0
Requires-Dist: pyyaml>=6.0.2
Requires-Dist: sqlite-utils>=3.38
